COPYING
LICENSE
MANIFEST.in
README.rst
pyproject.toml
doc/index.rst
src/lddecay/__init__.py
src/lddecay/cli.py
src/lddecay/version.py
src/lddecay.egg-info/PKG-INFO
src/lddecay.egg-info/SOURCES.txt
src/lddecay.egg-info/dependency_links.txt
src/lddecay.egg-info/entry_points.txt
src/lddecay.egg-info/requires.txt
src/lddecay.egg-info/top_level.txt
test/b.bcf
test/check-version.py
test/test.sh