Metadata-Version: 2.4
Name: lddecay
Version: 0.2.8
Summary: LD decay analysis using EggLib.
Author-email: Stéphane De Mita <demita@gmail.com>
License:                     GNU GENERAL PUBLIC LICENSE
Project-URL: Homepage, https://lddecay.readthedocs.io/
Project-URL: Download, https://pypi.org/project/lddecay/
Project-URL: Source, https://gitlab.com/demita/lddecay/
Classifier: Programming Language :: Python :: 3.13
Classifier: License :: OSI Approved :: GNU General Public License v3 or later (GPLv3+)
Classifier: Operating System :: OS Independent
Requires-Python: >=3.10
License-File: LICENSE
License-File: COPYING
Requires-Dist: egglib~=3.4
Requires-Dist: click
Requires-Dist: matplotlib
Dynamic: license-file
